pypci/__init__.py
pypci/__main__.py
pypci/backend/__init__.py
pypci/backend/device.py
pypci/backend/driver.py
pypci/backend/pci.py
pypci/backend/util.py
pypci/data/pci.class
pypci/data/pci.class.json
pypci/data/pci.data
pypci/data/pci.data.json
pypci/data/pci.ids
pypci/pypciException/__init__.py
pypci/pypciException/pypciException.py
pypci/pypciUtil/__init__.py
pypci/pypciUtil/pypciUtil.py
pypci_ng-0.3.3.dist-info/licenses/LICENSE
pypci_ng-0.3.3.dist-info/METADATA
pypci_ng-0.3.3.dist-info/WHEEL
pypci_ng-0.3.3.dist-info/entry_points.txt
pypci_ng-0.3.3.dist-info/top_level.txt
pypci_ng-0.3.3.dist-info/RECORD
