Metadata-Version: 2.4
Name: pypci-ng
Version: 0.3.3
Summary: pypci, a pciutils-like library for fetching system PCI/PCI-E information but written mostly in python.
Author: Xiao Ran
Maintainer-email: Xiao Ran <xiaoran.007@icloud.com>
License-Expression: BSD-3-Clause
Project-URL: homepage, https://github.com/xiaoran007/pypci
Keywords: pci,system information,pciutils,python,lspci,hardware information,fetching,pcie
Classifier: Development Status :: 5 - Production/Stable
Classifier: Programming Language :: Python :: 3
Classifier: Operating System :: OS Independent
Requires-Python: >=3.9
License-File: LICENSE
Dynamic: license-file
